sarasvati/__init__.py
sarasvati/api/__init__.py
sarasvati/api/sarasvati.py
sarasvati/app.py
sarasvati/brain/__init__.py
sarasvati/brain/brain.py
sarasvati/brain/components/__init__.py
sarasvati/brain/components/info.py
sarasvati/brain/components/manager.py
sarasvati/brain/components/provider.py
sarasvati/brain/manager.py
sarasvati/brain/models.py
sarasvati/brain/serialization.py
sarasvati/brain/storage/__init__.py
sarasvati/brain/storage/cache.py
sarasvati/brain/storage/storage.py
sarasvati/commands/__init__.py
sarasvati/commands/command.py
sarasvati/config/__init__.py
sarasvati/config/manager.py
sarasvati/config_handlers.py
sarasvati/core/event.py
sarasvati/packages/__init__.py
sarasvati/packages/exceptions.py
sarasvati/packages/fetcher.py
sarasvati/packages/manager.py
sarasvati/packages/metadata/__init__.py
sarasvati/packages/metadata/http_loader.py
sarasvati/packages/metadata/metadata.py
sarasvati/packages/metadata/yaml_parser.py
sarasvati/packages/package.py
sarasvati/packages/repository.py
sarasvati/plugins/__init__.py
sarasvati/plugins/interfaces.py
sarasvati/plugins/manager.py
sarasvati/storage/__init__.py
sarasvati/storage/helpers.py
sarasvati/storage/storage.py
sarasvati-0.1.2.dist-info/entry_points.txt
sarasvati-0.1.2.dist-info/LICENSE
sarasvati-0.1.2.dist-info/WHEEL
sarasvati-0.1.2.dist-info/METADATA
sarasvati-0.1.2.dist-info/RECORD
