Metadata-Version: 2.1
Name: sarasvati
Version: 0.1.2
Summary: 
Author: Advaita Krishna das
Author-email: advaita.krishna.das@gmail.com
Requires-Python: >=3.7,<4.0
Classifier: Programming Language :: Python :: 3
Classifier: Programming Language :: Python :: 3.7
Requires-Dist: ansimarkup (>=1.4,<2.0)
Requires-Dist: autoflake (>=1.3,<2.0)
Requires-Dist: hashids (>=1.2,<2.0)
Requires-Dist: munch (>=2.3,<3.0)
Requires-Dist: prompt_toolkit (>=2.0,<3.0)
Requires-Dist: pygments (>=2.4,<3.0)
Requires-Dist: pyqt5 (>=5.13,<6.0)
Requires-Dist: pyyaml (>=5.1,<6.0)
Requires-Dist: requests (>=2.22,<3.0)
Requires-Dist: tinydb (>=3.13,<4.0)
Requires-Dist: yapsy (>=1.12,<2.0)
